dj_wordpress-0.10.1.dist-info/DESCRIPTION.rst
dj_wordpress-0.10.1.dist-info/METADATA
dj_wordpress-0.10.1.dist-info/RECORD
dj_wordpress-0.10.1.dist-info/WHEEL
dj_wordpress-0.10.1.dist-info/metadata.json
dj_wordpress-0.10.1.dist-info/top_level.txt
wordpress/__init__.py
wordpress/admin.py
wordpress/exceptions.py
wordpress/models.py
wordpress/router.py
wordpress/urls.py
wordpress/views.py
wordpress/templates/wordpress/post_archive.html
wordpress/templates/wordpress/post_archive_author.html
wordpress/templates/wordpress/post_archive_day.html
wordpress/templates/wordpress/post_archive_month.html
wordpress/templates/wordpress/post_archive_year.html
wordpress/templates/wordpress/post_detail.html
wordpress/templates/wordpress/post_term.html
wordpress/templates/wordpress/wxr.xml
