Metadata-Version: 2.0
Name: dj-wordpress
Version: 0.10.1
Summary: Django models and views for a WordPress database.
Home-page: http://github.com/bennylope/dj-wordpress/
Author: Ben Lopatin
Author-email: ben@benlopatin.com
License: BSD License
Platform: any
Classifier: Development Status :: 4 - Beta
Classifier: Intended Audience :: Developers
Classifier: License :: OSI Approved :: BSD License
Classifier: Natural Language :: English
Classifier: Operating System :: OS Independent
Classifier: Programming Language :: Python
Classifier: Environment :: Web Environment
